pyngsi/__init__.py
pyngsi/__main__.py
pyngsi/agent.py
pyngsi/config.py
pyngsi/ftpclient.py
pyngsi/ngsi.py
pyngsi/scheduler.py
pyngsi/sink.py
pyngsi/sources/__init__.py
pyngsi/sources/more_sources.py
pyngsi/sources/server.py
pyngsi/sources/source.py
pyngsi/sources/source_ftp.py
pyngsi/sources/source_json.py
pyngsi/sources/source_mqtt.py
pyngsi/utils/__init__.py
pyngsi/utils/eyaml.py
pyngsi/utils/iso8601.py
pyngsi/utils/mqttclient.py
pyngsi/utils/stream.py
pyngsi-2.1.10.dist-info/LICENSE
pyngsi-2.1.10.dist-info/METADATA
pyngsi-2.1.10.dist-info/WHEEL
pyngsi-2.1.10.dist-info/top_level.txt
pyngsi-2.1.10.dist-info/RECORD
