Metadata-Version: 2.1
Name: pyngsi
Version: 2.1.10
Summary: NGSI Python framework intended to build a Fiware NGSI Agent
Home-page: https://github.com/Orange-OpenSource/pyngsi
Author: Orange OpenSource
Author-email: fabien.battello@orange.com
License: Apache 2.0
Platform: UNKNOWN
Classifier: License :: OSI Approved :: Apache Software License
Classifier: Operating System :: OS Independent
Classifier: Development Status :: 5 - Production/Stable
Classifier: Intended Audience :: Developers
Classifier: Programming Language :: Python :: 3
Classifier: Programming Language :: Python :: 3.8
Classifier: Programming Language :: Python :: 3.9
Requires-Python: >=3.8
License-File: LICENSE
Requires-Dist: loguru
Requires-Dist: requests
Requires-Dist: requests-toolbelt
Requires-Dist: shortuuid
Requires-Dist: more-itertools
Requires-Dist: geojson
Requires-Dist: flask
Requires-Dist: cherrypy
Requires-Dist: schedule
Requires-Dist: defusedxml
Requires-Dist: openpyxl
Requires-Dist: paho-mqtt
Requires-Dist: pyyaml
Requires-Dist: pandas
